vexmpp/__about__.py
vexmpp/__init__.py
vexmpp/_stringprep.py
vexmpp/client.py
vexmpp/errors.py
vexmpp/jid.py
vexmpp/metrics.py
vexmpp/namespaces.py
vexmpp/parser.py
vexmpp/ssl_transport.py
vexmpp/stanzas.py
vexmpp/stream.py
vexmpp/utils.py
vexmpp/features/__init__.py
vexmpp/features/bind.py
vexmpp/features/sasl.py
vexmpp/features/starttls.py
vexmpp/features/stream_mgmt.py
vexmpp/protocols/__init__.py
vexmpp/protocols/disco.py
vexmpp/protocols/entity_time.py
vexmpp/protocols/file_transfer.py
vexmpp/protocols/iqregister.py
vexmpp/protocols/iqroster.py
vexmpp/protocols/iqversion.py
vexmpp/protocols/muc.py
vexmpp/protocols/presence.py
vexmpp/protocols/resourcebind.py
vexmpp/protocols/sasl.py
vexmpp/protocols/sessionbind.py
vexmpp/protocols/stream_mgmt.py
vexmpp/protocols/vcard.py
vexmpp/protocols/xdata.py
vexmpp/suelta/__init__.py
vexmpp/suelta/exceptions.py
vexmpp/suelta/sasl.py
vexmpp/suelta/saslprep.py
vexmpp/suelta/util.py
vexmpp/suelta/mechanisms/__init__.py
vexmpp/suelta/mechanisms/anonymous.py
vexmpp/suelta/mechanisms/cram_md5.py
vexmpp/suelta/mechanisms/digest_md5.py
vexmpp/suelta/mechanisms/facebook_platform.py
vexmpp/suelta/mechanisms/messenger_oauth2.py
vexmpp/suelta/mechanisms/plain.py
vexmpp/suelta/mechanisms/scram_hmac.py
vexmpp/vex/__init__.py
vexmpp/vex/__main__.py
vexmpp/vex/util.py
vexmpp-0.1.3.dist-info/DESCRIPTION.rst
vexmpp-0.1.3.dist-info/LICENSE.txt
vexmpp-0.1.3.dist-info/METADATA
vexmpp-0.1.3.dist-info/RECORD
vexmpp-0.1.3.dist-info/WHEEL
vexmpp-0.1.3.dist-info/entry_points.txt
vexmpp-0.1.3.dist-info/metadata.json
vexmpp-0.1.3.dist-info/top_level.txt
