Metadata-Version: 2.0
Name: vexmpp
Version: 0.1.3
Summary: XMPP library for Python3 asyncio.
Home-page: https://github.com/nicfit/vexmpp
Author: Travis Shirk
Author-email: travis@pobox.com
License: MIT
Download-URL: https://github.com/nicfit/vexmpp/releases/downloads/v0.1.3/vexmpp-0.1.3.tar.gz
Keywords: vexmpp
Platform: Any
Classifier: Intended Audience :: Developers
Classifier: Operating System :: POSIX
Classifier: Natural Language :: English
Classifier: License :: OSI Approved :: MIT License
Classifier: Programming Language :: Python
Classifier: Programming Language :: Python :: 3.6
Classifier: Development Status :: 5 - Production/Stable
Requires-Dist: PyOpenSSL
Requires-Dist: lxml
Requires-Dist: aiodns
Requires-Dist: nicfit.py
